LICENSE
MANIFEST.in
README.md
requirements.txt
setup.py
oxasl/__init__.py
oxasl/_version.py
oxasl/brain.py
oxasl/calibration.py
oxasl/corrections.py
oxasl/distcorr.py
oxasl/epi_reg.py
oxasl/filtering.py
oxasl/image.py
oxasl/m0.py
oxasl/mask.py
oxasl/moco.py
oxasl/options.py
oxasl/output.py
oxasl/oxford_asl.py
oxasl/pipeline.py
oxasl/plugin.py
oxasl/preproc.py
oxasl/prequantify.py
oxasl/quantify.py
oxasl/quasil.py
oxasl/reg.py
oxasl/region_analysis.py
oxasl/reporting.py
oxasl/rois.py
oxasl/senscorr.py
oxasl/struc.py
oxasl/utils.py
oxasl/workspace.py
oxasl.egg-info/PKG-INFO
oxasl.egg-info/SOURCES.txt
oxasl.egg-info/dependency_links.txt
oxasl.egg-info/entry_points.txt
oxasl.egg-info/requires.txt
oxasl.egg-info/top_level.txt
oxasl/basil/__init__.py
oxasl/basil/fabber_method.py
oxasl/basil/multistep_fit.py
oxasl/basil/svb_method.py
oxasl/basil/vaby_method.py
oxasl/basil/svb/__init__.py
oxasl/gui/__init__.py
oxasl/gui/analysis_tab.py
oxasl/gui/banner.png
oxasl/gui/calib_tab.py
oxasl/gui/dist_corr_tab.py
oxasl/gui/icon.png
oxasl/gui/input_tab.py
oxasl/gui/run_box.py
oxasl/gui/structure_tab.py
oxasl/gui/widgets.py
oxasl/test/__init__.py
oxasl/test/test_basil.py
oxasl/test/test_calib.py
oxasl/test/test_image.py
oxasl/test/test_preproc.py
oxasl/test/test_reg.py
oxasl/test/test_workspace.py
oxasl/wrappers/__init__.py
oxasl/wrappers/avscale.py
oxasl/wrappers/epi_reg.py
oxasl/wrappers/fabber.py
oxasl/wrappers/fnirt_extra.py